ch06/__init__.py
ch06/mcp_client.py
ch06/weather.py
ch07/__init__.py
ch07/weather.py
mcp_weather_demo_cjy-0.1.0.dist-info/METADATA
mcp_weather_demo_cjy-0.1.0.dist-info/WHEEL
mcp_weather_demo_cjy-0.1.0.dist-info/entry_points.txt
mcp_weather_demo_cjy-0.1.0.dist-info/top_level.txt
mcp_weather_demo_cjy-0.1.0.dist-info/RECORD
