Metadata-Version: 2.4
Name: mcp-weather-demo-cjy
Version: 0.1.0
Summary: Add your description here
Requires-Python: >=3.10
Requires-Dist: httpx>=0.28.1
Requires-Dist: mcp>=1.12.0
Requires-Dist: openai>=1.97.0
Requires-Dist: python-dotenv>=1.1.1
